dc43_integrations/__init__.py
dc43_integrations/examples/__init__.py
dc43_integrations/examples/databricks_delta_versioning_support.py
dc43_integrations/setup_bundle/__init__.py
dc43_integrations/setup_bundle/dlt/__init__.py
dc43_integrations/setup_bundle/dlt/pipeline_stub.py
dc43_integrations/setup_bundle/spark/__init__.py
dc43_integrations/setup_bundle/spark/pipeline_stub.py
dc43_integrations/spark/__init__.py
dc43_integrations/spark/contracts.py
dc43_integrations/spark/data_quality.py
dc43_integrations/spark/dlt.py
dc43_integrations/spark/dlt_local.py
dc43_integrations/spark/io.py
dc43_integrations/spark/open_data_lineage.py
dc43_integrations/spark/open_telemetry.py
dc43_integrations/spark/validation.py
dc43_integrations/spark/violation_strategy.py
dc43_integrations/testing/__init__.py
dc43_integrations/testing/datasets.py
dc43_integrations-0.32.0.0.dist-info/METADATA
dc43_integrations-0.32.0.0.dist-info/WHEEL
dc43_integrations-0.32.0.0.dist-info/top_level.txt
dc43_integrations-0.32.0.0.dist-info/RECORD
